Calculate/__init__.py
Calculate/calc.py
useless_calc-0.0.1.dist-info/LICENSE
useless_calc-0.0.1.dist-info/METADATA
useless_calc-0.0.1.dist-info/WHEEL
useless_calc-0.0.1.dist-info/top_level.txt
useless_calc-0.0.1.dist-info/RECORD
