Metadata-Version: 2.1
Name: useless-calc
Version: 0.0.1
Summary: dont use this.
Home-page: https://github.com/jagadeesh-r1/calculate_silly
Author: Jagadeesh Reddy
Author-email: mail4jagadeeshreddy@gmail.com
License: GNU General Public License v3.0
Platform: UNKNOWN
